tests/__init__.py
tests/test_cli.py
tests/test_formatter.py
tests/fixtures/large.csv
tests/fixtures/small.csv
tests/fixtures/with_comments.csv
tests/fixtures/with_js_comments.csv
vl/__init__.py
vl/cli.py
vl/formatter.py
vl/pager.py
vl/py.typed
vl_csv_viewer-0.4.7.dist-info/METADATA
vl_csv_viewer-0.4.7.dist-info/WHEEL
vl_csv_viewer-0.4.7.dist-info/entry_points.txt
vl_csv_viewer-0.4.7.dist-info/top_level.txt
vl_csv_viewer-0.4.7.dist-info/RECORD
