Metadata-Version: 2.2
Name: vl-csv-viewer
Version: 0.4.7
Summary: An ultrafast CSV viewer in terminals
Home-page: https://github.com/w9/vl-csv-viewer
Author: Contributors
Author-email: user@example.com
Project-URL: Bug Tracker, https://github.com/w9/vl-csv-viewer/issues
Project-URL: Source Code, https://github.com/w9/vl-csv-viewer
Keywords: csv,viewer,terminal,console,table,data,visualization
Classifier: Development Status :: 4 - Beta
Classifier: Environment :: Console
Classifier: Intended Audience :: Developers
Classifier: Intended Audience :: System Administrators
Classifier: Programming Language :: Python :: 3
Classifier: Programming Language :: Python :: 3.6
Classifier: Programming Language :: Python :: 3.7
Classifier: Programming Language :: Python :: 3.8
Classifier: Programming Language :: Python :: 3.9
Classifier: Programming Language :: Python :: 3.10
Classifier: Programming Language :: Python :: 3.11
Classifier: License :: OSI Approved :: MIT License
Classifier: Operating System :: OS Independent
Classifier: Topic :: Text Processing :: General
Classifier: Topic :: Utilities
Requires-Python: >=3.6
Requires-Dist: argcomplete>=1.0.0
Dynamic: author
Dynamic: author-email
Dynamic: classifier
Dynamic: description
Dynamic: description-content-type
Dynamic: home-page
Dynamic: keywords
Dynamic: project-url
Dynamic: requires-dist
Dynamic: requires-python
Dynamic: summary
